<?xml version="1.0" encoding="UTF-8"?> <mxfile host="ac.draw.io" modified="2023-12-26T20:52:41.622Z" agent="Mozilla/5.0 (Macintosh; Intel Mac OS X 10_15_7) AppleWebKit/605.1.15 (KHTML, like Gecko) Version/17.1.2 Safari/605.1.15" etag="_h9CpMpl5jf-1ISfx5c0" version="22.1.11" type="embed"> <diagram id="062rsdyExYzQiWweLIWf" name="Page-1"> <mxGraphModel dx="1026" dy="753" grid="1" gridSize="10" guides="1" tooltips="1" connect="1" arrows="1" fold="1" page="1" pageScale="1" pageWidth="850" pageHeight="1100" math="0" shadow="0"> <root> <mxCell id="0"/> <mxCell id="1" parent="0"/> <mxCell id="EV6RpqzHmRYbOMt5xpLA-2" value="Command event" style="edgeStyle=orthogonalEdgeStyle;rounded=0;orthogonalLoop=1;jettySize=auto;html=1;exitX=1;exitY=0.25;exitDx=0;exitDy=0;entryX=0;entryY=0.25;entryDx=0;entryDy=0;dashed=1;" parent="1" source="EV6RpqzHmRYbOMt5xpLA-3" target="EV6RpqzHmRYbOMt5xpLA-8" edge="1"> <mxGeometry relative="1" as="geometry"/> </mxCell> <mxCell id="EV6RpqzHmRYbOMt5xpLA-3" value="Service" style="rounded=0;whiteSpace=wrap;html=1;" parent="1" vertex="1"> <mxGeometry x="220" y="660" width="120" height="60" as="geometry"/> </mxCell> <mxCell id="EV6RpqzHmRYbOMt5xpLA-4" value="REST" style="edgeStyle=orthogonalEdgeStyle;rounded=0;orthogonalLoop=1;jettySize=auto;html=1;entryX=0;entryY=0.5;entryDx=0;entryDy=0;" parent="1" source="EV6RpqzHmRYbOMt5xpLA-5" target="EV6RpqzHmRYbOMt5xpLA-3" edge="1"> <mxGeometry relative="1" as="geometry"/> </mxCell> <mxCell id="EV6RpqzHmRYbOMt5xpLA-5" value="Actor" style="shape=umlActor;verticalLabelPosition=bottom;verticalAlign=top;html=1;outlineConnect=0;" parent="1" vertex="1"> <mxGeometry x="50" y="660" width="30" height="60" as="geometry"/> </mxCell> <mxCell id="EV6RpqzHmRYbOMt5xpLA-7" value="Reply event" style="edgeStyle=orthogonalEdgeStyle;rounded=0;orthogonalLoop=1;jettySize=auto;html=1;exitX=0;exitY=0.75;exitDx=0;exitDy=0;entryX=1;entryY=0.75;entryDx=0;entryDy=0;dashed=1;" parent="1" source="EV6RpqzHmRYbOMt5xpLA-8" target="EV6RpqzHmRYbOMt5xpLA-3" edge="1"> <mxGeometry relative="1" as="geometry"> <mxPoint as="offset"/> </mxGeometry> </mxCell> <mxCell id="EV6RpqzHmRYbOMt5xpLA-8" value="Service" style="rounded=0;whiteSpace=wrap;html=1;" parent="1" vertex="1"> <mxGeometry x="690" y="660" width="120" height="60" as="geometry"/> </mxCell> <mxCell id="EV6RpqzHmRYbOMt5xpLA-11" value="Command event" style="rounded=0;orthogonalLoop=1;jettySize=auto;html=1;exitX=1;exitY=0.25;exitDx=0;exitDy=0;entryX=0;entryY=0.25;entryDx=0;entryDy=0;dashed=1;" parent="1" source="EV6RpqzHmRYbOMt5xpLA-13" target="EV6RpqzHmRYbOMt5xpLA-18" edge="1"> <mxGeometry relative="1" as="geometry"/> </mxCell> <mxCell id="EV6RpqzHmRYbOMt5xpLA-12" value="Command event" style="rounded=0;orthogonalLoop=1;jettySize=auto;html=1;exitX=1;exitY=0.75;exitDx=0;exitDy=0;entryX=0;entryY=0.25;entryDx=0;entryDy=0;dashed=1;" parent="1" source="EV6RpqzHmRYbOMt5xpLA-13" target="EV6RpqzHmRYbOMt5xpLA-22" edge="1"> <mxGeometry relative="1" as="geometry"/> </mxCell> <mxCell id="EV6RpqzHmRYbOMt5xpLA-13" value="Orchestrator &lt;br&gt;Service" style="rounded=0;whiteSpace=wrap;html=1;" parent="1" vertex="1"> <mxGeometry x="215" y="840" width="120" height="60" as="geometry"/> </mxCell> <mxCell id="EV6RpqzHmRYbOMt5xpLA-14" value="REST" style="edgeStyle=orthogonalEdgeStyle;rounded=0;orthogonalLoop=1;jettySize=auto;html=1;entryX=0;entryY=0.5;entryDx=0;entryDy=0;" parent="1" source="EV6RpqzHmRYbOMt5xpLA-15" target="EV6RpqzHmRYbOMt5xpLA-13" edge="1"> <mxGeometry relative="1" as="geometry"/> </mxCell> <mxCell id="EV6RpqzHmRYbOMt5xpLA-15" value="Actor" style="shape=umlActor;verticalLabelPosition=bottom;verticalAlign=top;html=1;outlineConnect=0;" parent="1" vertex="1"> <mxGeometry x="45" y="840" width="30" height="60" as="geometry"/> </mxCell> <mxCell id="EV6RpqzHmRYbOMt5xpLA-17" value="Reply event" style="rounded=0;orthogonalLoop=1;jettySize=auto;html=1;exitX=0;exitY=0.75;exitDx=0;exitDy=0;entryX=1;entryY=0.25;entryDx=0;entryDy=0;dashed=1;" parent="1" source="EV6RpqzHmRYbOMt5xpLA-18" target="EV6RpqzHmRYbOMt5xpLA-13" edge="1"> <mxGeometry relative="1" as="geometry"/> </mxCell> <mxCell id="EV6RpqzHmRYbOMt5xpLA-18" value="Service" style="rounded=0;whiteSpace=wrap;html=1;" parent="1" vertex="1"> <mxGeometry x="685" y="790" width="120" height="60" as="geometry"/> </mxCell> <mxCell id="EV6RpqzHmRYbOMt5xpLA-21" value="Reply event" style="rounded=0;orthogonalLoop=1;jettySize=auto;html=1;exitX=0;exitY=0.75;exitDx=0;exitDy=0;entryX=1;entryY=0.75;entryDx=0;entryDy=0;dashed=1;" parent="1" source="EV6RpqzHmRYbOMt5xpLA-22" target="EV6RpqzHmRYbOMt5xpLA-13" edge="1"> <mxGeometry relative="1" as="geometry"/> </mxCell> <mxCell id="EV6RpqzHmRYbOMt5xpLA-22" value="Service" style="rounded=0;whiteSpace=wrap;html=1;" parent="1" vertex="1"> <mxGeometry x="685" y="880" width="120" height="60" as="geometry"/> </mxCell> <mxCell id="64wo2PbFOHnvUE0VdYQ4-2" value="Command event" style="rounded=0;orthogonalLoop=1;jettySize=auto;html=1;exitX=1;exitY=0.25;exitDx=0;exitDy=0;entryX=0;entryY=0.25;entryDx=0;entryDy=0;dashed=1;" parent="1" source="64wo2PbFOHnvUE0VdYQ4-4" target="64wo2PbFOHnvUE0VdYQ4-9" edge="1"> <mxGeometry relative="1" as="geometry"/> </mxCell> <mxCell id="64wo2PbFOHnvUE0VdYQ4-4" value="Orchestrator &lt;br&gt;Service" style="rounded=0;whiteSpace=wrap;html=1;" parent="1" vertex="1"> <mxGeometry x="215" y="1060" width="120" height="60" as="geometry"/> </mxCell> <mxCell id="64wo2PbFOHnvUE0VdYQ4-5" value="REST" style="edgeStyle=orthogonalEdgeStyle;rounded=0;orthogonalLoop=1;jettySize=auto;html=1;entryX=0;entryY=0.5;entryDx=0;entryDy=0;" parent="1" source="64wo2PbFOHnvUE0VdYQ4-6" target="64wo2PbFOHnvUE0VdYQ4-4" edge="1"> <mxGeometry relative="1" as="geometry"/> </mxCell> <mxCell id="64wo2PbFOHnvUE0VdYQ4-6" value="Actor" style="shape=umlActor;verticalLabelPosition=bottom;verticalAlign=top;html=1;outlineConnect=0;" parent="1" vertex="1"> <mxGeometry x="45" y="1060" width="30" height="60" as="geometry"/> </mxCell> <mxCell id="64wo2PbFOHnvUE0VdYQ4-8" value="Command event" style="rounded=0;orthogonalLoop=1;jettySize=auto;html=1;exitX=0.5;exitY=1;exitDx=0;exitDy=0;entryX=0.5;entryY=0;entryDx=0;entryDy=0;dashed=1;" parent="1" source="64wo2PbFOHnvUE0VdYQ4-9" target="64wo2PbFOHnvUE0VdYQ4-13" edge="1"> <mxGeometry relative="1" as="geometry"/> </mxCell> <mxCell id="64wo2PbFOHnvUE0VdYQ4-9" value="Service" style="rounded=0;whiteSpace=wrap;html=1;" parent="1" vertex="1"> <mxGeometry x="685" y="1010" width="120" height="60" as="geometry"/> </mxCell> <mxCell id="64wo2PbFOHnvUE0VdYQ4-12" value="Reply event" style="rounded=0;orthogonalLoop=1;jettySize=auto;html=1;exitX=0;exitY=0.75;exitDx=0;exitDy=0;entryX=1;entryY=0.75;entryDx=0;entryDy=0;dashed=1;" parent="1" source="64wo2PbFOHnvUE0VdYQ4-13" target="64wo2PbFOHnvUE0VdYQ4-4" edge="1"> <mxGeometry relative="1" as="geometry"/> </mxCell> <mxCell id="64wo2PbFOHnvUE0VdYQ4-13" value="Service" style="rounded=0;whiteSpace=wrap;html=1;" parent="1" vertex="1"> <mxGeometry x="685" y="1150" width="120" height="60" as="geometry"/> </mxCell> </root> </mxGraphModel> </diagram> </mxfile>